odm_hlp_decorations/__init__.py
odm_hlp_decorations-1.0.1.dist-info/licenses/LICENSE
odm_hlp_decorations-1.0.1.dist-info/METADATA
odm_hlp_decorations-1.0.1.dist-info/WHEEL
odm_hlp_decorations-1.0.1.dist-info/RECORD
